silero_tts/__main__.py
silero_tts/lang_data.py
silero_tts/silero_tts.py
silero_tts/transliterate.py
silero_tts-0.0.5.dist-info/METADATA
silero_tts-0.0.5.dist-info/WHEEL
silero_tts-0.0.5.dist-info/licenses/LICENSE
silero_tts-0.0.5.dist-info/RECORD
