Metadata-Version: 2.3
Name: silero-tts
Version: 0.0.5
Summary: Script over the official Silero so that it can be conveniently and quickly used from the code or from the console
Project-URL: Homepage, https://github.com/daswer123/silero_cli
Project-URL: Bug Tracker, https://github.com/daswer123/silero_cli/issues
Author-email: daswer123 <daswerq123@gmail.com>
License-File: LICENSE
Classifier: License :: OSI Approved :: MIT License
Classifier: Operating System :: OS Independent
Classifier: Programming Language :: Python :: 3
Requires-Python: >=3.9
Requires-Dist: loguru
Requires-Dist: number2text
Requires-Dist: numpy
Requires-Dist: omegaconf
Requires-Dist: pyyaml
Requires-Dist: requests
Requires-Dist: torch
Requires-Dist: torchaudio
Requires-Dist: tqdm
